updatehdr/__init__.py
updatehdr/do_work.py
updatehdr/jobs/__init__.py
updatehdr/jobs/parser.py
updatehdr/jobs/processor.py
updatehdr-1.0.4.dist-info/METADATA
updatehdr-1.0.4.dist-info/WHEEL
updatehdr-1.0.4.dist-info/entry_points.txt
updatehdr-1.0.4.dist-info/top_level.txt
updatehdr-1.0.4.dist-info/RECORD
